odd_sorter/__init__.py
odd_sorter/core.py
odd_sorter-0.2.0.dist-info/METADATA
odd_sorter-0.2.0.dist-info/WHEEL
odd_sorter-0.2.0.dist-info/top_level.txt
odd_sorter-0.2.0.dist-info/RECORD
